[
  {
    "id": "c7860993-7c54-481b-88bd-9dc00fab4b19",
    "todo": "Learn Swedish",
    "priority": "LOW",
    "dueDate": "2025-03-31",
    "isDeleted": false
  },
  {
    "id": "be21f88b-ba6c-4ffd-998f-a2ee512e0834",
    "todo": "Learn NODE JS",
    "priority": "HIGH",
    "dueDate": "2024-04-30",
    "isDeleted": false
  },
  {
    "id": "8990d474-49f6-4964-b058-cffb0cc7bf89",
    "todo": "Learn REACT",
    "priority": "MEDIUM",
    "dueDate": "2024-03-31",
    "isDeleted": false
  },
  {
    "id": "b02234fd-0d90-43a0-bcde-95b439c7bd5c",
    "todo": "Learn Swedish",
    "priority": "LOW",
    "dueDate": "2025-03-31",
    "isDeleted": false
  },
  {
    "id": "39268440-7caa-4ac2-b6d1-e5c6ce286622",
    "todo": "Learn Python",
    "priority": "HIGH",
    "dueDate": "2025-03-31",
    "isDeleted": false
  },
  {
    "id": "55b17d61-f796-4576-a5d2-fe02e245feba",
    "todo": "Learn Swedish",
    "priority": "LOW",
    "dueDate": "2025-03-31",
    "isDeleted": false
  }
]